tsfresh_ppi/__init__.py
tsfresh_ppi-2021.8.29.dist-info/LICENSE
tsfresh_ppi-2021.8.29.dist-info/METADATA
tsfresh_ppi-2021.8.29.dist-info/WHEEL
tsfresh_ppi-2021.8.29.dist-info/top_level.txt
tsfresh_ppi-2021.8.29.dist-info/RECORD
