Metadata-Version: 2.1
Name: tsfresh-ppi
Version: 2021.8.29
Summary: Add peak-to-peak interval features to tsfresh
Home-page: https://github.com/atpage/tsfresh_ppi
Author: Alex Page
Author-email: a.t.page@gmail.com
License: UNKNOWN
Project-URL: Bug Tracker, https://github.com/atpage/tsfresh_ppi/issues
Platform: UNKNOWN
Classifier: Programming Language :: Python :: 3
Classifier: License :: OSI Approved :: MIT License
License-File: LICENSE
